{
"meta":{"test_sets":[],"test_metrics":[],"learn_metrics":[{"best_value":"Min","name":"RMSE"}],"launch_mode":"Train","parameters":"","iteration_count":300,"learn_sets":["learn"],"name":"experiment"},
"iterations":[
{"learn":[72445.30615],"iteration":0,"passed_time":0.08860157544,"remaining_time":26.49187106},
{"learn":[68109.65664],"iteration":1,"passed_time":0.1019504132,"remaining_time":15.19061156},
{"learn":[63975.07698],"iteration":2,"passed_time":0.1130639414,"remaining_time":11.1933302},
{"learn":[60117.54172],"iteration":3,"passed_time":0.1206422442,"remaining_time":8.927526071},
{"learn":[56716.34094],"iteration":4,"passed_time":0.1280552803,"remaining_time":7.555261535},
{"learn":[53433.07972],"iteration":5,"passed_time":0.132671456,"remaining_time":6.500901344},
{"learn":[50704.68608],"iteration":6,"passed_time":0.1384116713,"remaining_time":5.793517101},
{"learn":[48306.64393],"iteration":7,"passed_time":0.1470690788,"remaining_time":5.368021377},
{"learn":[46058.4706],"iteration":8,"passed_time":0.151174011,"remaining_time":4.887959689},
{"learn":[43973.11519],"iteration":9,"passed_time":0.1563530882,"remaining_time":4.534239559},
{"learn":[42129.87099],"iteration":10,"passed_time":0.1622396785,"remaining_time":4.262478825},
{"learn":[40571.1013],"iteration":11,"passed_time":0.1666072644,"remaining_time":3.998574344},
{"learn":[39132.20384],"iteration":12,"passed_time":0.1726784588,"remaining_time":3.812209053},
{"learn":[37822.88472],"iteration":13,"passed_time":0.179511567,"remaining_time":3.667164869},
{"learn":[36445.63679],"iteration":14,"passed_time":0.1862234239,"remaining_time":3.538245055},
{"learn":[35216.71408],"iteration":15,"passed_time":0.1896978183,"remaining_time":3.367136274},
{"learn":[34080.94471],"iteration":16,"passed_time":0.1941189756,"remaining_time":3.231510006},
{"learn":[33021.57939],"iteration":17,"passed_time":0.1982867512,"remaining_time":3.106492435},
{"learn":[32020.32181],"iteration":18,"passed_time":0.203129694,"remaining_time":3.004181264},
{"learn":[31238.0806],"iteration":19,"passed_time":0.2092510174,"remaining_time":2.929514243},
{"learn":[30356.47919],"iteration":20,"passed_time":0.2141214745,"remaining_time":2.844756733},
{"learn":[29479.68089],"iteration":21,"passed_time":0.2216933569,"remaining_time":2.801397873},
{"learn":[28839.25565],"iteration":22,"passed_time":0.228345127,"remaining_time":2.750069573},
{"learn":[28121.73225],"iteration":23,"passed_time":0.2365340439,"remaining_time":2.720141505},
{"learn":[27489.00523],"iteration":24,"passed_time":0.2441970239,"remaining_time":2.686167263},
{"learn":[26912.83306],"iteration":25,"passed_time":0.2515789636,"remaining_time":2.651255232},
{"learn":[26396.72392],"iteration":26,"passed_time":0.2592242597,"remaining_time":2.621045293},
{"learn":[25781.28446],"iteration":27,"passed_time":0.2662516631,"remaining_time":2.586444727},
{"learn":[25253.56398],"iteration":28,"passed_time":0.2734537684,"remaining_time":2.555378318},
{"learn":[24774.38236],"iteration":29,"passed_time":0.2803386122,"remaining_time":2.52304751},
{"learn":[24464.5184],"iteration":30,"passed_time":0.2887610708,"remaining_time":2.505700905},
{"learn":[24104.28688],"iteration":31,"passed_time":0.2957773369,"remaining_time":2.477135197},
{"learn":[23840.82644],"iteration":32,"passed_time":0.3044983348,"remaining_time":2.463668345},
{"learn":[23515.19458],"iteration":33,"passed_time":0.3118272686,"remaining_time":2.439589807},
{"learn":[23209.59061],"iteration":34,"passed_time":0.3202545296,"remaining_time":2.424784296},
{"learn":[22926.47213],"iteration":35,"passed_time":0.328771825,"remaining_time":2.410993383},
{"learn":[22715.80793],"iteration":36,"passed_time":0.3378836599,"remaining_time":2.401713582},
{"learn":[22440.89132],"iteration":37,"passed_time":0.3453973468,"remaining_time":2.381423812},
{"learn":[22113.02623],"iteration":38,"passed_time":0.3538921323,"remaining_time":2.368355039},
{"learn":[21815.60284],"iteration":39,"passed_time":0.3627474655,"remaining_time":2.357858526},
{"learn":[21599.30646],"iteration":40,"passed_time":0.3715574747,"remaining_time":2.347155755},
{"learn":[21358.7992],"iteration":41,"passed_time":0.3810459181,"remaining_time":2.34071064},
{"learn":[21147.57042],"iteration":42,"passed_time":0.3904608122,"remaining_time":2.333684389},
{"learn":[20959.91786],"iteration":43,"passed_time":0.4008283015,"remaining_time":2.332091936},
{"learn":[20764.60638],"iteration":44,"passed_time":0.4088712293,"remaining_time":2.316936966},
{"learn":[20648.28892],"iteration":45,"passed_time":0.4183269895,"remaining_time":2.309892507},
{"learn":[20417.86885],"iteration":46,"passed_time":0.4269179197,"remaining_time":2.298090079},
{"learn":[20238.29743],"iteration":47,"passed_time":0.4339271316,"remaining_time":2.278117441},
{"learn":[19992.7644],"iteration":48,"passed_time":0.4402039613,"remaining_time":2.254922332},
{"learn":[19880.13514],"iteration":49,"passed_time":0.4480720711,"remaining_time":2.240360355},
{"learn":[19648.36676],"iteration":50,"passed_time":0.455520519,"remaining_time":2.224011946},
{"learn":[19452.88009],"iteration":51,"passed_time":0.4618030497,"remaining_time":2.202445314},
{"learn":[19330.69023],"iteration":52,"passed_time":0.4737066617,"remaining_time":2.207651801},
{"learn":[19186.78121],"iteration":53,"passed_time":0.4834969823,"remaining_time":2.202597364},
{"learn":[19065.27659],"iteration":54,"passed_time":0.490345238,"remaining_time":2.184265151},
{"learn":[18972.34156],"iteration":55,"passed_time":0.4993239996,"remaining_time":2.175625998},
{"learn":[18829.93603],"iteration":56,"passed_time":0.5056144837,"remaining_time":2.155514378},
{"learn":[18687.5946],"iteration":57,"passed_time":0.5150472775,"remaining_time":2.148990365},
{"learn":[18587.05879],"iteration":58,"passed_time":0.5214305449,"remaining_time":2.129911209},
{"learn":[18433.34372],"iteration":59,"passed_time":0.5298333356,"remaining_time":2.119333342},
{"learn":[18319.87073],"iteration":60,"passed_time":0.5359509369,"remaining_time":2.099873343},
{"learn":[18218.51134],"iteration":61,"passed_time":0.5423437616,"remaining_time":2.081900246},
{"learn":[18129.44553],"iteration":62,"passed_time":0.5510187398,"remaining_time":2.072880021},
{"learn":[18032.46022],"iteration":63,"passed_time":0.5554012295,"remaining_time":2.048042034},
{"learn":[17919.16475],"iteration":64,"passed_time":0.5613427196,"remaining_time":2.029469833},
{"learn":[17834.92513],"iteration":65,"passed_time":0.5666858048,"remaining_time":2.009158763},
{"learn":[17647.55646],"iteration":66,"passed_time":0.5739012626,"remaining_time":1.995805883},
{"learn":[17512.8539],"iteration":67,"passed_time":0.5815018035,"remaining_time":1.98394733},
{"learn":[17348.71258],"iteration":68,"passed_time":0.5891255414,"remaining_time":1.972289856},
{"learn":[17287.61869],"iteration":69,"passed_time":0.5976591886,"remaining_time":1.963737334},
{"learn":[17164.5365],"iteration":70,"passed_time":0.6052238675,"remaining_time":1.95206008},
{"learn":[17106.40718],"iteration":71,"passed_time":0.6138178691,"remaining_time":1.943756585},
{"learn":[17025.49568],"iteration":72,"passed_time":0.6193770184,"remaining_time":1.926007989},
{"learn":[16891.03241],"iteration":73,"passed_time":0.6261675106,"remaining_time":1.912349424},
{"learn":[16811.83759],"iteration":74,"passed_time":0.6319928472,"remaining_time":1.895978542},
{"learn":[16735.98101],"iteration":75,"passed_time":0.6396381772,"remaining_time":1.885249364},
{"learn":[16674.87221],"iteration":76,"passed_time":0.6458990157,"remaining_time":1.870590656},
{"learn":[16607.94119],"iteration":77,"passed_time":0.6527735872,"remaining_time":1.857894056},
{"learn":[16532.39217],"iteration":78,"passed_time":0.6588900021,"remaining_time":1.84322393},
{"learn":[16447.8838],"iteration":79,"passed_time":0.6660885579,"remaining_time":1.831743534},
{"learn":[16339.31677],"iteration":80,"passed_time":0.6735270005,"remaining_time":1.821017446},
{"learn":[16264.2088],"iteration":81,"passed_time":0.6831365103,"remaining_time":1.816143405},
{"learn":[16182.33183],"iteration":82,"passed_time":0.6921917306,"remaining_time":1.809706091},
{"learn":[16103.27962],"iteration":83,"passed_time":0.7003321838,"remaining_time":1.800854187},
{"learn":[16035.36264],"iteration":84,"passed_time":0.7087494367,"remaining_time":1.792719163},
{"learn":[15939.31437],"iteration":85,"passed_time":0.7160537832,"remaining_time":1.781808251},
{"learn":[15810.85026],"iteration":86,"passed_time":0.7243275833,"remaining_time":1.773353738},
{"learn":[15735.59482],"iteration":87,"passed_time":0.7305573578,"remaining_time":1.759979089},
{"learn":[15643.13467],"iteration":88,"passed_time":0.7356844695,"remaining_time":1.744150821},
{"learn":[15586.67861],"iteration":89,"passed_time":0.7430203805,"remaining_time":1.733714221},
{"learn":[15479.98574],"iteration":90,"passed_time":0.7503731773,"remaining_time":1.72338455},
{"learn":[15410.30805],"iteration":91,"passed_time":0.7559457976,"remaining_time":1.709094847},
{"learn":[15325.42967],"iteration":92,"passed_time":0.7611413141,"remaining_time":1.694153248},
{"learn":[15266.81656],"iteration":93,"passed_time":0.7662399699,"remaining_time":1.679206742},
{"learn":[15199.75184],"iteration":94,"passed_time":0.7724455408,"remaining_time":1.666856167},
{"learn":[15124.60451],"iteration":95,"passed_time":0.7777967778,"remaining_time":1.652818153},
{"learn":[15021.72993],"iteration":96,"passed_time":0.7834032382,"remaining_time":1.639493375},
{"learn":[14950.07531],"iteration":97,"passed_time":0.789282123,"remaining_time":1.626887641},
{"learn":[14913.08362],"iteration":98,"passed_time":0.7948309229,"remaining_time":1.613747631},
{"learn":[14829.73346],"iteration":99,"passed_time":0.799821765,"remaining_time":1.59964353},
{"learn":[14765.06538],"iteration":100,"passed_time":0.8062378022,"remaining_time":1.588527947},
{"learn":[14686.06226],"iteration":101,"passed_time":0.8115373664,"remaining_time":1.575337241},
{"learn":[14600.8109],"iteration":102,"passed_time":0.8167470582,"remaining_time":1.562127869},
{"learn":[14541.98675],"iteration":103,"passed_time":0.8272364664,"remaining_time":1.559022571},
{"learn":[14492.69875],"iteration":104,"passed_time":0.8370868135,"remaining_time":1.554589797},
{"learn":[14436.54354],"iteration":105,"passed_time":0.8421241587,"remaining_time":1.541246102},
{"learn":[14381.40051],"iteration":106,"passed_time":0.8487695425,"remaining_time":1.530958147},
{"learn":[14338.14267],"iteration":107,"passed_time":0.8556862835,"remaining_time":1.52122006},
{"learn":[14222.11875],"iteration":108,"passed_time":0.8647052803,"remaining_time":1.51521751},
{"learn":[14112.53561],"iteration":109,"passed_time":0.8719039584,"remaining_time":1.506015928},
{"learn":[14039.80892],"iteration":110,"passed_time":0.8802941683,"remaining_time":1.49887926},
{"learn":[13954.95191],"iteration":111,"passed_time":0.8861874102,"remaining_time":1.487528867},
{"learn":[13898.7685],"iteration":112,"passed_time":0.8925451896,"remaining_time":1.477043809},
{"learn":[13842.69667],"iteration":113,"passed_time":0.8999021478,"remaining_time":1.468261399},
{"learn":[13799.43285],"iteration":114,"passed_time":0.9085082841,"remaining_time":1.461513327},
{"learn":[13687.85893],"iteration":115,"passed_time":0.9143923296,"remaining_time":1.450415419},
{"learn":[13638.56568],"iteration":116,"passed_time":0.9207262431,"remaining_time":1.440110278},
{"learn":[13565.69622],"iteration":117,"passed_time":0.9269275971,"remaining_time":1.429667989},
{"learn":[13508.97745],"iteration":118,"passed_time":0.9345838197,"remaining_time":1.421509843},
{"learn":[13452.35712],"iteration":119,"passed_time":0.944639767,"remaining_time":1.416959651},
{"learn":[13398.30685],"iteration":120,"passed_time":0.9511514699,"remaining_time":1.407075315},
{"learn":[13366.11029],"iteration":121,"passed_time":0.9600806541,"remaining_time":1.400773413},
{"learn":[13277.92949],"iteration":122,"passed_time":0.9651664765,"remaining_time":1.3888981},
{"learn":[13197.77097],"iteration":123,"passed_time":0.9698653896,"remaining_time":1.376583134},
{"learn":[13121.7282],"iteration":124,"passed_time":0.9763549344,"remaining_time":1.366896908},
{"learn":[13064.05897],"iteration":125,"passed_time":0.9822279075,"remaining_time":1.356409968},
{"learn":[13037.61415],"iteration":126,"passed_time":0.9930939404,"remaining_time":1.352797257},
{"learn":[12984.55049],"iteration":127,"passed_time":0.9979834217,"remaining_time":1.341040223},
{"learn":[12959.47344],"iteration":128,"passed_time":1.007089749,"remaining_time":1.334979435},
{"learn":[12896.24163],"iteration":129,"passed_time":1.014653473,"remaining_time":1.326854542},
{"learn":[12837.72026],"iteration":130,"passed_time":1.023141541,"remaining_time":1.319930691},
{"learn":[12785.53205],"iteration":131,"passed_time":1.030600431,"remaining_time":1.311673276},
{"learn":[12731.77087],"iteration":132,"passed_time":1.043379661,"remaining_time":1.310108297},
{"learn":[12684.00052],"iteration":133,"passed_time":1.059119176,"remaining_time":1.312043159},
{"learn":[12653.39441],"iteration":134,"passed_time":1.077649726,"remaining_time":1.317127443},
{"learn":[12617.29041],"iteration":135,"passed_time":1.088725659,"remaining_time":1.312875059},
{"learn":[12577.23734],"iteration":136,"passed_time":1.097087081,"remaining_time":1.305293388},
{"learn":[12516.70433],"iteration":137,"passed_time":1.105806683,"remaining_time":1.298120889},
{"learn":[12473.57265],"iteration":138,"passed_time":1.114647819,"remaining_time":1.291066898},
{"learn":[12445.56268],"iteration":139,"passed_time":1.12404499,"remaining_time":1.284622846},
{"learn":[12415.67788],"iteration":140,"passed_time":1.130723183,"remaining_time":1.275070823},
{"learn":[12369.82544],"iteration":141,"passed_time":1.136097448,"remaining_time":1.264108428},
{"learn":[12330.90106],"iteration":142,"passed_time":1.143607319,"remaining_time":1.255568875},
{"learn":[12258.52056],"iteration":143,"passed_time":1.150078476,"remaining_time":1.245918349},
{"learn":[12200.0751],"iteration":144,"passed_time":1.157634652,"remaining_time":1.237471525},
{"learn":[12166.29929],"iteration":145,"passed_time":1.163241637,"remaining_time":1.226980905},
{"learn":[12144.65726],"iteration":146,"passed_time":1.169745078,"remaining_time":1.217489775},
{"learn":[12095.81395],"iteration":147,"passed_time":1.176947436,"remaining_time":1.208756826},
{"learn":[12057.21946],"iteration":148,"passed_time":1.182923446,"remaining_time":1.198801613},
{"learn":[11996.90982],"iteration":149,"passed_time":1.18965203,"remaining_time":1.18965203},
{"learn":[11936.22966],"iteration":150,"passed_time":1.195177535,"remaining_time":1.179347369},
{"learn":[11883.02387],"iteration":151,"passed_time":1.200520151,"remaining_time":1.168927516},
{"learn":[11842.44865],"iteration":152,"passed_time":1.204983279,"remaining_time":1.157729033},
{"learn":[11796.95441],"iteration":153,"passed_time":1.21180472,"remaining_time":1.148853826},
{"learn":[11741.30947],"iteration":154,"passed_time":1.217721943,"remaining_time":1.139159237},
{"learn":[11709.63895],"iteration":155,"passed_time":1.223089144,"remaining_time":1.129005364},
{"learn":[11663.18179],"iteration":156,"passed_time":1.228486791,"remaining_time":1.118940198},
{"learn":[11644.09989],"iteration":157,"passed_time":1.234861548,"remaining_time":1.109812277},
{"learn":[11580.6581],"iteration":158,"passed_time":1.239315393,"remaining_time":1.099015537},
{"learn":[11536.72972],"iteration":159,"passed_time":1.245682132,"remaining_time":1.089971865},
{"learn":[11516.50047],"iteration":160,"passed_time":1.252018112,"remaining_time":1.080934892},
{"learn":[11474.86985],"iteration":161,"passed_time":1.258560051,"remaining_time":1.07210671},
{"learn":[11411.03476],"iteration":162,"passed_time":1.2654345,"remaining_time":1.063586052},
{"learn":[11362.32169],"iteration":163,"passed_time":1.271075296,"remaining_time":1.054062441},
{"learn":[11292.3816],"iteration":164,"passed_time":1.275970112,"remaining_time":1.043975546},
{"learn":[11266.04342],"iteration":165,"passed_time":1.280335616,"remaining_time":1.033523931},
{"learn":[11237.4924],"iteration":166,"passed_time":1.285313103,"remaining_time":1.023632591},
{"learn":[11192.00997],"iteration":167,"passed_time":1.290334838,"remaining_time":1.013834515},
{"learn":[11133.70156],"iteration":168,"passed_time":1.294793851,"remaining_time":1.003656772},
{"learn":[11075.25013],"iteration":169,"passed_time":1.304776263,"remaining_time":0.9977700837},
{"learn":[11040.91984],"iteration":170,"passed_time":1.311495817,"remaining_time":0.9893740372},
{"learn":[11012.91471],"iteration":171,"passed_time":1.320226225,"remaining_time":0.982493935},
{"learn":[10985.5513],"iteration":172,"passed_time":1.327542191,"remaining_time":0.9745540938},
{"learn":[10948.14171],"iteration":173,"passed_time":1.332973417,"remaining_time":0.9652566125},
{"learn":[10918.22311],"iteration":174,"passed_time":1.34048212,"remaining_time":0.9574872288},
{"learn":[10872.28179],"iteration":175,"passed_time":1.3471709,"remaining_time":0.9491431342},
{"learn":[10845.10541],"iteration":176,"passed_time":1.353868244,"remaining_time":0.9408236951},
{"learn":[10818.15559],"iteration":177,"passed_time":1.361808874,"remaining_time":0.9333746214},
{"learn":[10769.78103],"iteration":178,"passed_time":1.371011055,"remaining_time":0.926772836},
{"learn":[10738.82635],"iteration":179,"passed_time":1.380504251,"remaining_time":0.920336167},
{"learn":[10707.64396],"iteration":180,"passed_time":1.388909619,"remaining_time":0.9131505228},
{"learn":[10666.36754],"iteration":181,"passed_time":1.397387989,"remaining_time":0.905998806},
{"learn":[10627.98904],"iteration":182,"passed_time":1.40504569,"remaining_time":0.8983079002},
{"learn":[10560.72813],"iteration":183,"passed_time":1.412955422,"remaining_time":0.8907762442},
{"learn":[10507.79106],"iteration":184,"passed_time":1.421679718,"remaining_time":0.8837468514},
{"learn":[10456.07628],"iteration":185,"passed_time":1.429737521,"remaining_time":0.8762907386},
{"learn":[10435.73983],"iteration":186,"passed_time":1.438297795,"remaining_time":0.8691318229},
{"learn":[10396.35714],"iteration":187,"passed_time":1.446839606,"remaining_time":0.8619469992},
{"learn":[10365.09471],"iteration":188,"passed_time":1.455639516,"remaining_time":0.8548993983},
{"learn":[10327.68874],"iteration":189,"passed_time":1.46582469,"remaining_time":0.8486353466},
{"learn":[10302.42753],"iteration":190,"passed_time":1.474254723,"remaining_time":0.8413286117},
{"learn":[10275.18668],"iteration":191,"passed_time":1.483692556,"remaining_time":0.8345770627},
{"learn":[10215.12223],"iteration":192,"passed_time":1.491247568,"remaining_time":0.8267538329},
{"learn":[10188.97886],"iteration":193,"passed_time":1.498858197,"remaining_time":0.8189637573},
{"learn":[10153.53475],"iteration":194,"passed_time":1.505921417,"remaining_time":0.8108807629},
{"learn":[10116.03974],"iteration":195,"passed_time":1.512746273,"remaining_time":0.8026816958},
{"learn":[10097.24643],"iteration":196,"passed_time":1.520744363,"remaining_time":0.7951099971},
{"learn":[10060.30419],"iteration":197,"passed_time":1.528504577,"remaining_time":0.7874114489},
{"learn":[10005.35992],"iteration":198,"passed_time":1.536557338,"remaining_time":0.7798607595},
{"learn":[9983.372512],"iteration":199,"passed_time":1.542817972,"remaining_time":0.7714089858},
{"learn":[9942.395128],"iteration":200,"passed_time":1.548737185,"remaining_time":0.7628108524},
{"learn":[9905.863868],"iteration":201,"passed_time":1.553901891,"remaining_time":0.7538731946},
{"learn":[9856.128728],"iteration":202,"passed_time":1.562783102,"remaining_time":0.7467485759},
{"learn":[9819.260355],"iteration":203,"passed_time":1.570474505,"remaining_time":0.7390468261},
{"learn":[9783.913925],"iteration":204,"passed_time":1.578358822,"remaining_time":0.7314345762},
{"learn":[9745.026241],"iteration":205,"passed_time":1.586467285,"remaining_time":0.7239219651},
{"learn":[9711.560821],"iteration":206,"passed_time":1.594014217,"remaining_time":0.7161513151},
{"learn":[9679.814893],"iteration":207,"passed_time":1.60005604,"remaining_time":0.7077170945},
{"learn":[9641.490998],"iteration":208,"passed_time":1.606748354,"remaining_time":0.6995889964},
{"learn":[9611.179452],"iteration":209,"passed_time":1.612835627,"remaining_time":0.6912152688},
{"learn":[9588.031487],"iteration":210,"passed_time":1.620334325,"remaining_time":0.6834585539},
{"learn":[9560.246121],"iteration":211,"passed_time":1.630556681,"remaining_time":0.6768348485},
{"learn":[9518.492284],"iteration":212,"passed_time":1.639159911,"remaining_time":0.6695160198},
{"learn":[9494.349564],"iteration":213,"passed_time":1.647738216,"remaining_time":0.6621751708},
{"learn":[9479.754799],"iteration":214,"passed_time":1.657442467,"remaining_time":0.655267952},
{"learn":[9439.113683],"iteration":215,"passed_time":1.669072513,"remaining_time":0.649083755},
{"learn":[9411.289411],"iteration":216,"passed_time":1.680598705,"remaining_time":0.6428096429},
{"learn":[9381.568086],"iteration":217,"passed_time":1.688848984,"remaining_time":0.6352551223},
{"learn":[9338.831254],"iteration":218,"passed_time":1.700622608,"remaining_time":0.6289974031},
{"learn":[9314.302394],"iteration":219,"passed_time":1.712757889,"remaining_time":0.6228210507},
{"learn":[9282.551749],"iteration":220,"passed_time":1.719262546,"remaining_time":0.6145780143},
{"learn":[9268.028903],"iteration":221,"passed_time":1.73754818,"remaining_time":0.6104899012},
{"learn":[9241.680958],"iteration":222,"passed_time":1.749222143,"remaining_time":0.6039915023},
{"learn":[9224.725407],"iteration":223,"passed_time":1.755464984,"remaining_time":0.5956041911},
{"learn":[9187.4769],"iteration":224,"passed_time":1.763327091,"remaining_time":0.5877756971},
{"learn":[9170.700234],"iteration":225,"passed_time":1.773261798,"remaining_time":0.5806255446},
{"learn":[9149.356534],"iteration":226,"passed_time":1.782762718,"remaining_time":0.5733113588},
{"learn":[9109.273816],"iteration":227,"passed_time":1.792070189,"remaining_time":0.5659169017},
{"learn":[9075.433744],"iteration":228,"passed_time":1.799507891,"remaining_time":0.5579260274},
{"learn":[9037.40724],"iteration":229,"passed_time":1.808085449,"remaining_time":0.5502868758},
{"learn":[8999.887877],"iteration":230,"passed_time":1.815914238,"remaining_time":0.5424159411},
{"learn":[8988.144084],"iteration":231,"passed_time":1.823359081,"remaining_time":0.5344328341},
{"learn":[8950.332086],"iteration":232,"passed_time":1.830614548,"remaining_time":0.5263998916},
{"learn":[8918.455724],"iteration":233,"passed_time":1.83929492,"remaining_time":0.5187754902},
{"learn":[8887.553165],"iteration":234,"passed_time":1.847728234,"remaining_time":0.5110737668},
{"learn":[8862.654871],"iteration":235,"passed_time":1.855198788,"remaining_time":0.503104756},
{"learn":[8843.362916],"iteration":236,"passed_time":1.862811708,"remaining_time":0.4951777958},
{"learn":[8800.929991],"iteration":237,"passed_time":1.870441502,"remaining_time":0.4872578702},
{"learn":[8791.297189],"iteration":238,"passed_time":1.877435598,"remaining_time":0.4791781234},
{"learn":[8764.11616],"iteration":239,"passed_time":1.885070799,"remaining_time":0.4712676996},
{"learn":[8733.760123],"iteration":240,"passed_time":1.894333114,"remaining_time":0.4637578992},
{"learn":[8724.869763],"iteration":241,"passed_time":1.899589305,"remaining_time":0.4552734699},
{"learn":[8697.172834],"iteration":242,"passed_time":1.907125833,"remaining_time":0.4473505041},
{"learn":[8668.759785],"iteration":243,"passed_time":1.915445643,"remaining_time":0.4396104754},
{"learn":[8626.571967],"iteration":244,"passed_time":1.923726981,"remaining_time":0.4318570774},
{"learn":[8607.222812],"iteration":245,"passed_time":1.93141567,"remaining_time":0.4239692934},
{"learn":[8599.059493],"iteration":246,"passed_time":1.938591875,"remaining_time":0.4159731553},
{"learn":[8562.542678],"iteration":247,"passed_time":1.946689894,"remaining_time":0.4081769133},
{"learn":[8538.78253],"iteration":248,"passed_time":1.954891295,"remaining_time":0.4003994219},
{"learn":[8515.037215],"iteration":249,"passed_time":1.961841458,"remaining_time":0.3923682915},
{"learn":[8507.09207],"iteration":250,"passed_time":1.96721364,"remaining_time":0.3840377225},
{"learn":[8485.750782],"iteration":251,"passed_time":1.975984279,"remaining_time":0.3763779579},
{"learn":[8455.482131],"iteration":252,"passed_time":1.983901785,"remaining_time":0.3685509244},
{"learn":[8430.197495],"iteration":253,"passed_time":1.989585053,"remaining_time":0.3603185528},
{"learn":[8395.029428],"iteration":254,"passed_time":1.993863907,"remaining_time":0.3518583364},
{"learn":[8374.333357],"iteration":255,"passed_time":1.99957262,"remaining_time":0.3436765441},
{"learn":[8351.547133],"iteration":256,"passed_time":2.005651574,"remaining_time":0.3355759443},
{"learn":[8309.629913],"iteration":257,"passed_time":2.013479947,"remaining_time":0.3277758054},
{"learn":[8272.704358],"iteration":258,"passed_time":2.021898751,"remaining_time":0.3200689142},
{"learn":[8248.83124],"iteration":259,"passed_time":2.029026204,"remaining_time":0.3121578775},
{"learn":[8227.814315],"iteration":260,"passed_time":2.037340023,"remaining_time":0.3044301184},
{"learn":[8210.164368],"iteration":261,"passed_time":2.043545123,"remaining_time":0.2963920407},
{"learn":[8191.285437],"iteration":262,"passed_time":2.052330615,"remaining_time":0.288730923},
{"learn":[8180.443711],"iteration":263,"passed_time":2.060833494,"remaining_time":0.2810227492},
{"learn":[8162.05951],"iteration":264,"passed_time":2.068660531,"remaining_time":0.2732193154},
{"learn":[8138.203724],"iteration":265,"passed_time":2.07746879,"remaining_time":0.2655411236},
{"learn":[8119.904341],"iteration":266,"passed_time":2.085293323,"remaining_time":0.2577328826},
{"learn":[8084.177939],"iteration":267,"passed_time":2.092745162,"remaining_time":0.2498800193},
{"learn":[8052.115682],"iteration":268,"passed_time":2.101108339,"remaining_time":0.2421351617},
{"learn":[8015.781774],"iteration":269,"passed_time":2.109670094,"remaining_time":0.2344077882},
{"learn":[8002.469428],"iteration":270,"passed_time":2.117555466,"remaining_time":0.2266018764},
{"learn":[7996.503663],"iteration":271,"passed_time":2.127175033,"remaining_time":0.2189739004},
{"learn":[7978.698945],"iteration":272,"passed_time":2.135693653,"remaining_time":0.2112224492},
{"learn":[7953.199965],"iteration":273,"passed_time":2.144833474,"remaining_time":0.2035243442},
{"learn":[7932.039452],"iteration":274,"passed_time":2.155610655,"remaining_time":0.195964605},
{"learn":[7901.87584],"iteration":275,"passed_time":2.163097649,"remaining_time":0.1880954478},
{"learn":[7871.56783],"iteration":276,"passed_time":2.169054824,"remaining_time":0.1801020251},
{"learn":[7843.965613],"iteration":277,"passed_time":2.175429414,"remaining_time":0.1721562845},
{"learn":[7821.995892],"iteration":278,"passed_time":2.18222696,"remaining_time":0.1642536422},
{"learn":[7794.620255],"iteration":279,"passed_time":2.190630193,"remaining_time":0.1564735852},
{"learn":[7767.239741],"iteration":280,"passed_time":2.198509344,"remaining_time":0.1486536567},
{"learn":[7756.883896],"iteration":281,"passed_time":2.206027934,"remaining_time":0.1408102936},
{"learn":[7731.478205],"iteration":282,"passed_time":2.214169507,"remaining_time":0.1330066488},
{"learn":[7716.808158],"iteration":283,"passed_time":2.223263441,"remaining_time":0.1252542784},
{"learn":[7696.419784],"iteration":284,"passed_time":2.229430392,"remaining_time":0.1173384417},
{"learn":[7662.314058],"iteration":285,"passed_time":2.238063767,"remaining_time":0.109555569},
{"learn":[7658.563361],"iteration":286,"passed_time":2.245642844,"remaining_time":0.1017190138},
{"learn":[7628.505806],"iteration":287,"passed_time":2.253925759,"remaining_time":0.09391357329},
{"learn":[7611.42594],"iteration":288,"passed_time":2.260619709,"remaining_time":0.08604434878},
{"learn":[7581.325321],"iteration":289,"passed_time":2.270179665,"remaining_time":0.07828205743},
{"learn":[7564.46219],"iteration":290,"passed_time":2.278606994,"remaining_time":0.07047238125},
{"learn":[7539.310493],"iteration":291,"passed_time":2.288766241,"remaining_time":0.06270592441},
{"learn":[7524.621828],"iteration":292,"passed_time":2.295887217,"remaining_time":0.05485054784},
{"learn":[7504.489532],"iteration":293,"passed_time":2.304728429,"remaining_time":0.04703527406},
{"learn":[7488.241305],"iteration":294,"passed_time":2.312233435,"remaining_time":0.0391903972},
{"learn":[7469.401572],"iteration":295,"passed_time":2.320854324,"remaining_time":0.03136289627},
{"learn":[7442.625611],"iteration":296,"passed_time":2.327284945,"remaining_time":0.02350792874},
{"learn":[7434.503764],"iteration":297,"passed_time":2.333982036,"remaining_time":0.01566430897},
{"learn":[7410.634123],"iteration":298,"passed_time":2.342127675,"remaining_time":0.007833202925},
{"learn":[7387.93187],"iteration":299,"passed_time":2.348894409,"remaining_time":0}
]}